setup.py
distr_test/Binomialdistribution.py
distr_test/Gaussiandistribution.py
distr_test/Generaldistribution.py
distr_test/__init__.py
distr_test.egg-info/PKG-INFO
distr_test.egg-info/SOURCES.txt
distr_test.egg-info/dependency_links.txt
distr_test.egg-info/not-zip-safe
distr_test.egg-info/top_level.txt